fake_go_contacts.py
fake_go_contacts-0.1.9.dist-info/METADATA
fake_go_contacts-0.1.9.dist-info/RECORD
fake_go_contacts-0.1.9.dist-info/top_level.txt
fake_go_contacts-0.1.9.dist-info/metadata.json
fake_go_contacts-0.1.9.dist-info/WHEEL
fake_go_contacts-0.1.9.dist-info/DESCRIPTION.rst
